machi
