Metadata-Version: 2.1
Name: machi-store
Version: 0.0.8
Summary: Persistent Blob Store
Home-page: https://github.com/kuenishi/machi-py/
Author: Kota UENISHI
Author-email: kuenishi@gmail.com
License: UNKNOWN
Platform: UNKNOWN
Classifier: Development Status :: 3 - Alpha
Classifier: Intended Audience :: Developers
Classifier: License :: OSI Approved :: MIT License
Classifier: Programming Language :: Python :: 3.5
Classifier: Programming Language :: Python :: 3.6
Classifier: Programming Language :: Python :: 3.7
Requires-Python: >=3.5
Provides-Extra: test
